test/test_models/__init__.py
test/test_models/test_activity_kyc_model.py
test/test_models/test_add_transaction_action.py
test/test_models/test_agent_bank_withdrawal_transaction_model.py
test/test_models/test_agent_request_payment_transaction_model.py
test/test_models/test_agent_send_payment_transaction_model.py
test/test_models/test_approval_model.py
test/test_models/test_approval_status_model.py
test/test_models/test_category_model.py
test/test_models/test_category_property_model.py
test/test_models/test_contact_business_model.py
test/test_models/test_contact_model.py
test/test_models/test_country_model.py
test/test_models/test_credential_model.py
test/test_models/test_currency_item_model.py
test/test_models/test_description_model.py
test/test_models/test_document_model.py
test/test_models/test_document_type_model.py
test/test_models/test_error_model.py
test/test_models/test_isg_pay_model.py
test/test_models/test_item_detail_model.py
test/test_models/test_item_list_model.py
test/test_models/test_item_property_model.py
test/test_models/test_ledger_banking_model.py
test/test_models/test_linked_wallet_model.py
test/test_models/test_merchant_list_model.py
test/test_models/test_merchant_request_payment_transaction_model.py
test/test_models/test_message_model.py
test/test_models/test_message_page_model.py
test/test_models/test_meta_data_model.py
test/test_models/test_note_entity.py
test/test_models/test_otp_type.py
test/test_models/test_pending_transaction_status.py
test/test_models/test_preference_model.py
test/test_models/test_problem_details.py
test/test_models/test_profile_agent_location_model.py
test/test_models/test_profile_full_model.py
test/test_models/test_profile_model.py
test/test_models/test_profile_register_model.py
test/test_models/test_relationship_model.py
test/test_models/test_relationship_tran_model.py
test/test_models/test_report_column_model.py
test/test_models/test_report_heading_model.py
test/test_models/test_report_model.py
xprizo_sdk_py-1.0.1.dist-info/METADATA
xprizo_sdk_py-1.0.1.dist-info/WHEEL
xprizo_sdk_py-1.0.1.dist-info/top_level.txt
xprizo_sdk_py-1.0.1.dist-info/RECORD
